README.md
setup.cfg
setup.py
clementineremote/__init__.py
clementineremote/clementine.py
clementineremote/cli.py
clementineremote/remotecontrolmessages_pb2.py
python_clementine_remote.egg-info/PKG-INFO
python_clementine_remote.egg-info/SOURCES.txt
python_clementine_remote.egg-info/dependency_links.txt
python_clementine_remote.egg-info/entry_points.txt
python_clementine_remote.egg-info/requires.txt
python_clementine_remote.egg-info/top_level.txt