Metadata-Version: 1.1
Name: python-clementine-remote
Version: 1.0.3
Summary: Python library and CLI for the Clementine Music Player remote protocol.
Home-page: http://github.com/jjmontesl/python-clementine-remote
Author: Jose Juan Montes
Author-email: jjmontes@gmail.com
License: Apache Software License, Version 2.0
Platform: UNKNOWN
Classifier: Development Status :: 4 - Beta
Classifier: Intended Audience :: Developers
Classifier: License :: OSI Approved :: Apache Software License
Classifier: Operating System :: POSIX
Classifier: Programming Language :: Python
Classifier: Programming Language :: Python :: 2.7
Classifier: Programming Language :: Python :: 3
Classifier: Programming Language :: Python :: 3.2
Classifier: Programming Language :: Python :: 3.3
Classifier: Programming Language :: Python :: 3.4
Classifier: Programming Language :: Python :: 3.5
Classifier: Programming Language :: Python :: 3.6
